rbmpy/__init__.py
rbmpy/utilities.py
rbmpy/agent_rbm/AgentRbm.py
rbmpy/agent_rbm/AgentVarsRbm.py
rbmpy/agent_rbm/__init__.py
rbmpy/circular_regression/RegressionParent.py
rbmpy/circular_regression/__init__.py
rbmpy-0.0.2.dist-info/licenses/LICENSE
rbmpy-0.0.2.dist-info/METADATA
rbmpy-0.0.2.dist-info/WHEEL
rbmpy-0.0.2.dist-info/top_level.txt
rbmpy-0.0.2.dist-info/RECORD
