Metadata-Version: 2.4
Name: rbmpy
Version: 0.0.2
Summary: Python tools for the Reduced Bayesian Model (RBM): simulation, fitting, and analysis.
Author-email: Rasmus Bruckner <rasmusb@zedat.fu-berlin.de>
License: 
Project-URL: Source, https://github.com/rasmusbruckner/rbmpy
Project-URL: Documentation, https://rasmusbruckner.github.io/rbmpy/
Requires-Python: >=3.10
License-File: LICENSE
Requires-Dist: numpy
Requires-Dist: scipy
Requires-Dist: pandas
Requires-Dist: matplotlib
Requires-Dist: seaborn
Requires-Dist: allinpy
Requires-Dist: pycircstat2
Dynamic: license-file
